keyslib/__init__.py
keyslib/click_param.py
keyslib/exceptions.py
keyslib/parser.py
keyslib/printer.py
keyslib/scanner.py
keyslib/types.py
keyslib/visitor.py
keyslib/builder/__init__.py
keyslib/builder/utils.py
keyslib/cli/__init__.py
keyslib/cli/cli.py
keyslib/cli/context.py
keyslib/formatters/__init__.py
keyslib/formatters/hammerspoon.py
keyslib/formatters/tmux.py
keyslib/formatters/unicode.py
keyslib/formatters/vscode.py
keyslib/loader/__init__.py
keyslib-0.0.1.dist-info/LICENSE
keyslib-0.0.1.dist-info/METADATA
keyslib-0.0.1.dist-info/WHEEL
keyslib-0.0.1.dist-info/entry_points.txt
keyslib-0.0.1.dist-info/top_level.txt
keyslib-0.0.1.dist-info/RECORD
